fuzzy/__init__.py
fuzzy/categories.py
fuzzy/engine.py
fuzzy/memberships.py
fuzzy/rules.py
fuzzy/test_fuzzy/__init__.py
fuzzy/test_fuzzy/test_categories.py
fuzzy/test_fuzzy/test_engine.py
fuzzy/test_fuzzy/test_memberships.py
fuzzy/test_fuzzy/test_rules.py
inp_manage/__init__.py
inp_manage/inp.py
inp_manage/test_inp_manage/__init__.py
inp_manage/test_inp_manage/test_inp.py
fuzzy_catchments-0.0.2.dist-info/LICENSE
fuzzy_catchments-0.0.2.dist-info/METADATA
fuzzy_catchments-0.0.2.dist-info/WHEEL
fuzzy_catchments-0.0.2.dist-info/top_level.txt
fuzzy_catchments-0.0.2.dist-info/RECORD
