Metadata-Version: 2.1
Name: fuzzy-catchments
Version: 0.0.2
Summary: ('A tool for rapid prototyping of a hydraulic model catchments that can be read and edited with SWMM.',)
Author: Rafał Buczyński
Project-URL: Homepage, https://github.com/BuczynskiRafal/catchment_prototyping
License-File: LICENSE
Requires-Dist: scikit-fuzzy
Requires-Dist: numpy
Requires-Dist: pandas
Requires-Dist: matplotlib
Requires-Dist: swmmio
Requires-Dist: pyswmm
